fta_automl/FTAutoML.py
fta_automl/__init__.py
fta_automl/dataset.py
fta_automl-0.1.0.dist-info/licenses/LICENSE
fta_automl-0.1.0.dist-info/WHEEL
fta_automl-0.1.0.dist-info/METADATA
fta_automl-0.1.0.dist-info/RECORD
