Metadata-Version: 2.4
Name: fta_automl
Version: 0.1.0
Summary: Feel The Agi AutoML Library.
Author-email: Artem Goncharov <artemgoncarov943@gmail.com>
License-Expression: MIT
License-File: LICENSE
Requires-Dist: alembic==1.16.5
Requires-Dist: appnope==0.1.4
Requires-Dist: asttokens==3.0.0
Requires-Dist: catboost==1.2.8
Requires-Dist: colorlog==6.9.0
Requires-Dist: comm==0.2.3
Requires-Dist: contourpy==1.3.0
Requires-Dist: cycler==0.12.1
Requires-Dist: debugpy==1.8.17
Requires-Dist: decorator==5.2.1
Requires-Dist: exceptiongroup==1.3.0
Requires-Dist: executing==2.2.1
Requires-Dist: fonttools==4.60.0
Requires-Dist: graphviz==0.21
Requires-Dist: importlib_metadata==8.7.0
Requires-Dist: importlib_resources==6.5.2
Requires-Dist: ipykernel==6.30.1
Requires-Dist: ipython==8.18.1
Requires-Dist: ipywidgets==8.1.7
Requires-Dist: jedi==0.19.2
Requires-Dist: joblib==1.5.2
Requires-Dist: jupyter_client==8.6.3
Requires-Dist: jupyter_core==5.8.1
Requires-Dist: jupyterlab_widgets==3.0.15
Requires-Dist: kiwisolver==1.4.7
Requires-Dist: lightgbm==4.6.0
Requires-Dist: Mako==1.3.10
Requires-Dist: MarkupSafe==3.0.2
Requires-Dist: matplotlib==3.9.4
Requires-Dist: matplotlib-inline==0.1.7
Requires-Dist: narwhals==2.5.0
Requires-Dist: nest-asyncio==1.6.0
Requires-Dist: numpy==2.0.2
Requires-Dist: optuna==4.5.0
Requires-Dist: packaging==25.0
Requires-Dist: pandas==2.3.2
Requires-Dist: parso==0.8.5
Requires-Dist: pexpect==4.9.0
Requires-Dist: pillow==11.3.0
Requires-Dist: platformdirs==4.4.0
Requires-Dist: plotly==6.3.0
Requires-Dist: prompt_toolkit==3.0.52
Requires-Dist: psutil==7.1.0
Requires-Dist: ptyprocess==0.7.0
Requires-Dist: pure_eval==0.2.3
Requires-Dist: Pygments==2.19.2
Requires-Dist: pyparsing==3.2.4
Requires-Dist: python-dateutil==2.9.0.post0
Requires-Dist: pytz==2025.2
Requires-Dist: PyYAML==6.0.2
Requires-Dist: pyzmq==27.1.0
Requires-Dist: scikit-learn==1.6.1
Requires-Dist: scipy==1.13.1
Requires-Dist: six==1.17.0
Requires-Dist: SQLAlchemy==2.0.43
Requires-Dist: stack-data==0.6.3
Requires-Dist: threadpoolctl==3.6.0
Requires-Dist: tomli==2.2.1
Requires-Dist: tornado==6.5.2
Requires-Dist: tqdm==4.67.1
Requires-Dist: traitlets==5.14.3
Requires-Dist: typing_extensions==4.15.0
Requires-Dist: tzdata==2025.2
Requires-Dist: wcwidth==0.2.13
Requires-Dist: widgetsnbextension==4.0.14
Requires-Dist: xgboost==2.1.4
Requires-Dist: zipp==3.23.0
Project-URL: Home, https://github.com/artemgoncarov
